klaviyo_sdk/__init__.py
klaviyo_sdk/custom_retry.py
klaviyo_sdk/wrapper.py
swagger_client/__init__.py
swagger_client/api_client.py
swagger_client/configuration.py
swagger_client/rest.py
swagger_client/api/__init__.py
swagger_client/api/campaigns_api.py
swagger_client/api/data_privacy_api.py
swagger_client/api/lists__segments_api.py
swagger_client/api/metrics_api.py
swagger_client/api/profiles_api.py
swagger_client/api/templates_api.py
swagger_client/api/track__identify_api.py
swagger_client/models/__init__.py
swagger_client/models/ascending.py
swagger_client/models/campaign.py
swagger_client/models/campaign_campaign_id_body.py
swagger_client/models/campaign_id_clone_body.py
swagger_client/models/campaign_id_schedule_body.py
swagger_client/models/campaign_template.py
swagger_client/models/check_membership_request.py
swagger_client/models/check_membership_response.py
swagger_client/models/check_membership_response_inner.py
swagger_client/models/delete_email.py
swagger_client/models/delete_person.py
swagger_client/models/delete_phone.py
swagger_client/models/deprecated_get_list_response.py
swagger_client/models/deprecated_get_list_response_data.py
swagger_client/models/descending.py
swagger_client/models/emailtemplate_template_id_body.py
swagger_client/models/global_exclusion_response_data.py
swagger_client/models/global_exclusion_response_data_data.py
swagger_client/models/identify_payload.py
swagger_client/models/identify_payload_post.py
swagger_client/models/identify_payload_properties.py
swagger_client/models/inline_response200.py
swagger_client/models/inline_response2001.py
swagger_client/models/inline_response20010.py
swagger_client/models/inline_response20011.py
swagger_client/models/inline_response20011_data.py
swagger_client/models/inline_response20012.py
swagger_client/models/inline_response20012_data.py
swagger_client/models/inline_response20013.py
swagger_client/models/inline_response20014.py
swagger_client/models/inline_response2002.py
klaviyo_sdk-1.0.9.20220329.dist-info/LICENSE
klaviyo_sdk-1.0.9.20220329.dist-info/METADATA
klaviyo_sdk-1.0.9.20220329.dist-info/WHEEL
klaviyo_sdk-1.0.9.20220329.dist-info/top_level.txt
klaviyo_sdk-1.0.9.20220329.dist-info/RECORD
